Workbook

Sheet Balance
A1: Activo | B1: Peso | C1: Rendimiento | D1: Aporte rendimiento | E1: Pasivo | F1: Peso | G1: Costo | H1: Aporte costo
A2: Efectivo | B2: 0.1 | C2: 0.02 | D2: =B2*C2 -> 0.002 | E2: Vista | F2: 0.25 | G2: 0.01 | H2: =F2*G2 -> 0.0025
A3: Bonos Gobierno corto plazo | B3: 0.2 | C3: 0.05 | D3: =B3*C3 -> 0.01 | E3: Plazo público | F3: 0.3 | G3: 0.03 | H3: =F3*G3 -> 0.009
A4: Fondos inmobiliarios | B4: 0.2 | C4: 0.07 | D4: =B4*C4 -> 0.014 | E4: Fondeo institucional local | F4: 0.2 | G4: 0.07 | H4: =F4*G4 -> 0.014
A5: Cartera crédito 5 años plazo | B5: 0.2 | C5: 0.08 | D5: =B5*C5 -> 0.016 | E5: Fondeo en Bolsa | F5: 0.15 | G5: 0.08 | H5: =F5*G5 -> 0.012
A6: Cartera crédito largo plazo | B6: 0.3 | C6: 0.1 | D6: =B6*C6 -> 0.03 | E6: Fondeo institucional en US | F6: 0.1 | G6: 0.06 | H6: =F6*G6 -> 0.006
A8: Total activo | B8: =SUM(B2:B6) -> 1 | C8: =SUM(D2:D6) -> 0.072 | E8: Total pasivo | F8: =SUM(F2:F6) -> 1 | G8: =SUM(H2:H6) -> 0.0435
A10: Indicador | B10: Resultado
A11: Rendimiento promedio activo | B11: =C8 -> 0.072
A12: Costo promedio pasivo | B12: =G8 -> 0.0435
A13: Margen financiero actual | B13: =B11-B12 -> 0.0285

Sheet Liquidez
A1: Pasivo | B1: Peso | C1: Costo | D1: Supuesto
A2: Vista | B2: 0.25 | C2: 0.01 | D2: Distribución Normal; desviación promedio 2%.
A3: Plazo público | B3: 0.3 | C3: 0.03 | D3: Renovación 50%.
A4: Fondeo institucional local | B4: 0.2 | C4: 0.07 | D4: Vence > 2 años.
A5: Fondeo en Bolsa | B5: 0.15 | C5: 0.08 | D5: Mercado.
A6: Fondeo institucional en US | B6: 0.1 | C6: 0.06 | D6: Vence > 2 años.

Sheet Escenarios
A1: Activo | B1: Actual | C1: Escenario 1 (Moderado) | D1: Escenario Meta 5% | E1: Rendimiento | F1: Comentario
A2: Efectivo | B2: =+Balance!B2 -> 0.1 | C2: 0.08 | D2: 0.05 | E2: 0.02 | F2: Liquidez inmediata
A3: Bonos Gobierno corto plazo | B3: =+Balance!B3 -> 0.2 | C3: 0.15 | D3: 0.05 | E3: 0.05 | F3: Liquidez secundaria
A4: Fondos inmobiliarios | B4: =+Balance!B4 -> 0.2 | C4: 0.15 | D4: 0 | E4: 0.07 | F4: Menos líquido
A5: Cartera crédito 5 años | B5: =+Balance!B5 -> 0.2 | C5: 0.25 | D5: 0 | E5: 0.08 | F5: Productivo, requiere fondeo estable
A6: Cartera crédito largo plazo | B6: =+Balance!B6 -> 0.3 | C6: 0.37 | D6: 0.9 | E6: 0.1 | F6: Mayor rentabilidad y mayor descalce
A8: Indicador | B8: Actual | C8: Escenario 1 (Moderado) | D8: Escenario Meta 5%
A9: Total pesos | B9: =SUM(B2:B6) -> 1 | C9: =SUM(C2:C6) -> 1 | D9: =SUM(D2:D6) -> 1
A10: Rendimiento activo | B10: =SUMPRODUCT(B2:B6,$E$2:$E$6) -> 0.072 | C10: =SUMPRODUCT(C2:C6,$E$2:$E$6) -> 0.0766 | D10: =SUMPRODUCT(D2:D6,$E$2:$E$6) -> 0.0935
A11: Costo pasivo actual | B11: =Balance!G8 -> 0.0435 | C11: =Balance!G8 -> 0.0435 | D11: =Balance!G8 -> 0.0435
A12: Margen estimado | B12: =B10-B11 -> 0.0285 | C12: =C10-C11 -> 0.0331 | D12: =D10-D11 -> 0.05
A13: Liquidez total | B13: =B2+B3 -> 0.3 | C13: =C2+C3 -> 0.23 | D13: =D2+D3 -> 0.1

Sheet Fuentes
A1: Elemento | B1: Fuente | C1: Ubicación | D1: Uso
A2: Balance y supuestos del caso | B2: Enunciado del usuario | C2: Tabla de activo/pasivo y supuestos | D2: Cálculo de rendimiento, costo, margen y zonas de liquidez
A3: Definición de riesgo de liquidez | B3: Clase 6. 25 junio.pdf | C3: p. 2 | D3: Base conceptual
A4: Política de liquidez | B4: Clase 6. 25 junio.pdf | C4: p. 24 | D4: Composición, vencimiento, diversificación, moneda y activos líquidos
A5: Costo de la liquidez | B5: Clase 6. 25 junio.pdf | C5: p. 9 | D5: Costo de oportunidad de caja e inversiones
A6: Fondeo estable neto | B6: Clase 6. 25 junio.pdf | C6: p. 23 | D6: Relación entre activos y pasivos estables
A7: Pruebas de estrés | B7: Clase 6. 25 junio.pdf | C7: p. 47 | D7: Evaluar impacto del estrés y planes de contingencia

Sheet Reputacional
B3: Indicador | C3: Dato real | D3: Resultado encuesta | E3: Dato de la Competencia | F3: Industria | G3: Realidad | H3: Percepción
B4: Solvencia | C4: 0.13 | D4: 0.16 | E4: 0.17 | F4: 0.15 | G4: =(C4-$F4)/$F4 -> -0.13333333 | H4: =(D4-$F4)/$F4 -> 0.066666667
B5: Eficiencia de servicio | C5: 8 | D5: 7 | E5: 8 | F5: 7.5 | G5: =(C5-$F5)/$F5 -> 0.066666667 | H5: =(D5-$F5)/$F5 -> -0.066666667
B6: Buenos rendimientos | C6: 0.1 | D6: 0.08 | E6: 0.09 | F6: 0.065 | G6: =(C6-$F6)/$F6 -> 0.53846154 | H6: =(D6-$F6)/$F6 -> 0.23076923
B7: Cumplimiento regulatorio | C7: 0.75 | D7: 0.7 | E7: 0.6 | F7: 0.8 | G7: =(C7-$F7)/$F7 -> -0.0625 | H7: =(D7-$F7)/$F7 -> -0.125
B8: Pagos en tiempo óptimo | C8: 7 | D8: 9 | E8: 7 | F8: 10 | G8: =(-(C8-$F8)/$F8) -> 0.3 | H8: =(-(D8-$F8)/$F8) -> 0.1
B9: Incentivos por buen desempeño | C9: 0.4 | D9: 0.3 | E9: 0.2 | F9: 0.5 | G9: =(C9-$F9)/$F9 -> -0.2 | H9: =(D9-$F9)/$F9 -> -0.4
